gin.py
gin165-0.0.8.dist-info/DESCRIPTION.rst
gin165-0.0.8.dist-info/METADATA
gin165-0.0.8.dist-info/RECORD
gin165-0.0.8.dist-info/WHEEL
gin165-0.0.8.dist-info/entry_points.txt
gin165-0.0.8.dist-info/metadata.json
gin165-0.0.8.dist-info/top_level.txt
