Metadata-Version: 2.0
Name: gin165
Version: 0.0.8
Summary: Command line utility for my personal needs.
Home-page: UNKNOWN
Author: UNKNOWN
Author-email: UNKNOWN
License: UNKNOWN
Platform: UNKNOWN
Requires-Python: ~=3.6
Requires-Dist: Click
Requires-Dist: Pillow
Requires-Dist: svglib
Requires-Dist: twine
